takedown/__init__.py
takedown/takedown.py
takedown/client/BaseSite.py
takedown/client/GitHub.py
takedown/client/__init__.py
takedown/controller/InputProcessor.py
takedown/controller/InputReader.py
takedown/controller/OutputParser.py
takedown/controller/TaskExecutor.py
takedown/controller/__init__.py
takedown/task/BaseTask.py
takedown/task/FindRepoTask.py
takedown/task/SendEmailTask.py
takedown/task/__init__.py
takedown-0.1.1.dist-info/LICENSE
takedown-0.1.1.dist-info/METADATA
takedown-0.1.1.dist-info/WHEEL
takedown-0.1.1.dist-info/entry_points.txt
takedown-0.1.1.dist-info/top_level.txt
takedown-0.1.1.dist-info/RECORD
