Metadata-Version: 2.1
Name: takedown
Version: 0.1.1
Summary: A simple python script/package that allows users to search potential copyright violated information on GitHub
Home-page: https://github.com/zsxing99/Takedown-script
Author: Zesheng Xing
Author-email: zsxing@ucdavis.edu
License: UNKNOWN
Project-URL: GitHub, https://github.com/zsxing99/Takedown-script
Project-URL: GitLab, https://gitlab.com/luplab/luptakedown
Platform: UNKNOWN
Classifier: Programming Language :: Python :: 3
Classifier: License :: OSI Approved :: MIT License
Classifier: Operating System :: OS Independent
Requires-Python: >=3.5
Requires-Dist: requests (~=2.23.0)
Requires-Dist: PyYAML (~=5.3.1)
